sequence_pool_generator/__init__.py
sequence_pool_generator/__main__.py
sequence_pool_generator/example.py
sequence_pool_generator/generatePool.py
sequence_pool_generator/py.typed
sequence_pool_generator-0.2.0.dist-info/entry_points.txt
sequence_pool_generator-0.2.0.dist-info/LICENSE
sequence_pool_generator-0.2.0.dist-info/WHEEL
sequence_pool_generator-0.2.0.dist-info/METADATA
sequence_pool_generator-0.2.0.dist-info/RECORD
