Metadata-Version: 2.1
Name: sequence-pool-generator
Version: 0.2.0
Summary: A package to use monte carlo simulat
Home-page: https://github.com/sequence_pool_generator/sequence-pool-generator
License: MIT
Author: sequence-pool-generator
Author-email: hello@sequence-pool-generator.com
Requires-Python: >=3.7,<4.0
Classifier: Development Status :: 3 - Alpha
Classifier: Intended Audience :: Developers
Classifier: License :: OSI Approved :: MIT License
Classifier: Operating System :: OS Independent
Classifier: Programming Language :: Python :: 3
Classifier: Programming Language :: Python :: 3.7
Classifier: Programming Language :: Python :: 3.8
Classifier: Programming Language :: Python :: 3.9
Classifier: Topic :: Software Development :: Libraries :: Python Modules
Requires-Dist: biopython (>=1.79,<2.0)
Requires-Dist: importlib_metadata (>=4.5.0,<5.0.0); python_version < "3.8"
Requires-Dist: pytest (>=6.2.4,<7.0.0)
Requires-Dist: rich (>=10.4.0,<11.0.0)
Requires-Dist: typer[all] (>=0.3.2,<0.4.0)
Project-URL: Repository, https://github.com/sequence_pool_generator/sequence-pool-generator
